<?xml version="1.0" encoding="UTF-8" standalone="yes"?>
<worksheet xmlns="http://schemas.openxmlformats.org/spreadsheetml/2006/main" xmlns:r="http://schemas.openxmlformats.org/officeDocument/2006/relationships" xmlns:xdr="http://schemas.openxmlformats.org/drawingml/2006/spreadsheetDrawing" xmlns:x14="http://schemas.microsoft.com/office/spreadsheetml/2009/9/main" xmlns:mc="http://schemas.openxmlformats.org/markup-compatibility/2006" xmlns:etc="http://www.wps.cn/officeDocument/2017/etCustomData"><sheetPr/><dimension ref="A1:O89"/><sheetViews><sheetView showGridLines="0" workbookViewId="0"><selection activeCell="S6" sqref="S6"/></sheetView></sheetViews><sheetFormatPr defaultColWidth="9" defaultRowHeight="13.5"/><cols><col min="1" max="1" width="26.5" customWidth="1"/><col min="2" max="2" width="15.1333333333333" customWidth="1"/><col min="9" max="9" width="13" customWidth="1"/></cols><sheetData><row r="1" ht="87" customHeight="1" spans="2:10"><c r="B1" s="428" t="s"><v>5</v></c><c r="C1" s="428"/><c r="D1" s="428"/><c r="E1" s="428"/><c r="F1" s="428"/><c r="G1" s="428"/><c r="H1" s="428"/><c r="I1" s="428"/><c r="J1" s="428"/></row><row r="2" ht="21" spans="1:1"><c r="A2" s="24" t="s"><v>223</v></c></row><row r="3" ht="14.25" spans="2:9"><c r="B3" s="178" t="s"><v>2451</v></c><c r="I3" s="178" t="s"><v>2452</v></c></row><row r="4" spans="2:15"><c r="B4" s="429"/><c r="C4" s="429"/><c r="D4" s="429"/><c r="E4" s="429"/><c r="F4" s="429"/><c r="G4" s="429"/><c r="I4" s="429"/><c r="J4" s="429"/><c r="K4" s="429"/><c r="L4" s="429"/><c r="M4" s="429"/><c r="N4" s="429"/><c r="O4" s="429"/></row><row r="5" spans="2:15"><c r="B5" s="429"/><c r="C5" s="429"/><c r="D5" s="429"/><c r="E5" s="429"/><c r="F5" s="429"/><c r="G5" s="429"/><c r="I5" s="429"/><c r="J5" s="429"/><c r="K5" s="429"/><c r="L5" s="429"/><c r="M5" s="429"/><c r="N5" s="429"/><c r="O5" s="429"/></row><row r="6" spans="2:15"><c r="B6" s="429"/><c r="C6" s="429"/><c r="D6" s="429"/><c r="E6" s="429"/><c r="F6" s="429"/><c r="G6" s="429"/><c r="I6" s="429"/><c r="J6" s="429"/><c r="K6" s="429"/><c r="L6" s="429"/><c r="M6" s="429"/><c r="N6" s="429"/><c r="O6" s="429"/></row><row r="7" spans="2:15"><c r="B7" s="429"/><c r="C7" s="429"/><c r="D7" s="429"/><c r="E7" s="429"/><c r="F7" s="429"/><c r="G7" s="429"/><c r="I7" s="429"/><c r="J7" s="429"/><c r="K7" s="429"/><c r="L7" s="429"/><c r="M7" s="429"/><c r="N7" s="429"/><c r="O7" s="429"/></row><row r="8" spans="2:15"><c r="B8" s="429"/><c r="C8" s="429"/><c r="D8" s="429"/><c r="E8" s="429"/><c r="F8" s="429"/><c r="G8" s="429"/><c r="I8" s="429"/><c r="J8" s="429"/><c r="K8" s="429"/><c r="L8" s="429"/><c r="M8" s="429"/><c r="N8" s="429"/><c r="O8" s="429"/></row><row r="9" spans="2:15"><c r="B9" s="429"/><c r="C9" s="429"/><c r="D9" s="429"/><c r="E9" s="429"/><c r="F9" s="429"/><c r="G9" s="429"/><c r="I9" s="429"/><c r="J9" s="429"/><c r="K9" s="429"/><c r="L9" s="429"/><c r="M9" s="429"/><c r="N9" s="429"/><c r="O9" s="429"/></row><row r="10" spans="2:15"><c r="B10" s="429"/><c r="C10" s="429"/><c r="D10" s="429"/><c r="E10" s="429"/><c r="F10" s="429"/><c r="G10" s="429"/><c r="I10" s="429"/><c r="J10" s="429"/><c r="K10" s="429"/><c r="L10" s="429"/><c r="M10" s="429"/><c r="N10" s="429"/><c r="O10" s="429"/></row><row r="11" spans="2:15"><c r="B11" s="429"/><c r="C11" s="429"/><c r="D11" s="429"/><c r="E11" s="429"/><c r="F11" s="429"/><c r="G11" s="429"/><c r="I11" s="429"/><c r="J11" s="429"/><c r="K11" s="429"/><c r="L11" s="429"/><c r="M11" s="429"/><c r="N11" s="429"/><c r="O11" s="429"/></row><row r="12" spans="2:15"><c r="B12" s="429"/><c r="C12" s="429"/><c r="D12" s="429"/><c r="E12" s="429"/><c r="F12" s="429"/><c r="G12" s="429"/><c r="I12" s="429"/><c r="J12" s="429"/><c r="K12" s="429"/><c r="L12" s="429"/><c r="M12" s="429"/><c r="N12" s="429"/><c r="O12" s="429"/></row><row r="13" spans="2:15"><c r="B13" s="429"/><c r="C13" s="429"/><c r="D13" s="429"/><c r="E13" s="429"/><c r="F13" s="429"/><c r="G13" s="429"/><c r="I13" s="429"/><c r="J13" s="429"/><c r="K13" s="429"/><c r="L13" s="429"/><c r="M13" s="429"/><c r="N13" s="429"/><c r="O13" s="429"/></row><row r="14" spans="2:15"><c r="B14" s="429"/><c r="C14" s="429"/><c r="D14" s="429"/><c r="E14" s="429"/><c r="F14" s="429"/><c r="G14" s="429"/><c r="I14" s="429"/><c r="J14" s="429"/><c r="K14" s="429"/><c r="L14" s="429"/><c r="M14" s="429"/><c r="N14" s="429"/><c r="O14" s="429"/></row><row r="15" spans="2:15"><c r="B15" s="429"/><c r="C15" s="429"/><c r="D15" s="429"/><c r="E15" s="429"/><c r="F15" s="429"/><c r="G15" s="429"/><c r="I15" s="429"/><c r="J15" s="429"/><c r="K15" s="429"/><c r="L15" s="429"/><c r="M15" s="429"/><c r="N15" s="429"/><c r="O15" s="429"/></row><row r="16" spans="2:15"><c r="B16" s="429"/><c r="C16" s="429"/><c r="D16" s="429"/><c r="E16" s="429"/><c r="F16" s="429"/><c r="G16" s="429"/><c r="I16" s="429"/><c r="J16" s="429"/><c r="K16" s="429"/><c r="L16" s="429"/><c r="M16" s="429"/><c r="N16" s="429"/><c r="O16" s="429"/></row><row r="17" spans="2:15"><c r="B17" s="429"/><c r="C17" s="429"/><c r="D17" s="429"/><c r="E17" s="429"/><c r="F17" s="429"/><c r="G17" s="429"/><c r="I17" s="429"/><c r="J17" s="429"/><c r="K17" s="429"/><c r="L17" s="429"/><c r="M17" s="429"/><c r="N17" s="429"/><c r="O17" s="429"/></row><row r="18" spans="2:15"><c r="B18" s="429"/><c r="C18" s="429"/><c r="D18" s="429"/><c r="E18" s="429"/><c r="F18" s="429"/><c r="G18" s="429"/><c r="I18" s="429"/><c r="J18" s="429"/><c r="K18" s="429"/><c r="L18" s="429"/><c r="M18" s="429"/><c r="N18" s="429"/><c r="O18" s="429"/></row><row r="19" spans="2:15"><c r="B19" s="429"/><c r="C19" s="429"/><c r="D19" s="429"/><c r="E19" s="429"/><c r="F19" s="429"/><c r="G19" s="429"/><c r="I19" s="429"/><c r="J19" s="429"/><c r="K19" s="429"/><c r="L19" s="429"/><c r="M19" s="429"/><c r="N19" s="429"/><c r="O19" s="429"/></row><row r="20" spans="2:15"><c r="B20" s="429"/><c r="C20" s="429"/><c r="D20" s="429"/><c r="E20" s="429"/><c r="F20" s="429"/><c r="G20" s="429"/><c r="I20" s="429"/><c r="J20" s="429"/><c r="K20" s="429"/><c r="L20" s="429"/><c r="M20" s="429"/><c r="N20" s="429"/><c r="O20" s="429"/></row><row r="21" spans="2:15"><c r="B21" s="429"/><c r="C21" s="429"/><c r="D21" s="429"/><c r="E21" s="429"/><c r="F21" s="429"/><c r="G21" s="429"/><c r="I21" s="429"/><c r="J21" s="429"/><c r="K21" s="429"/><c r="L21" s="429"/><c r="M21" s="429"/><c r="N21" s="429"/><c r="O21" s="429"/></row><row r="22" spans="2:15"><c r="B22" s="429"/><c r="C22" s="429"/><c r="D22" s="429"/><c r="E22" s="429"/><c r="F22" s="429"/><c r="G22" s="429"/><c r="I22" s="429"/><c r="J22" s="429"/><c r="K22" s="429"/><c r="L22" s="429"/><c r="M22" s="429"/><c r="N22" s="429"/><c r="O22" s="429"/></row><row r="23" spans="2:15"><c r="B23" s="429"/><c r="C23" s="429"/><c r="D23" s="429"/><c r="E23" s="429"/><c r="F23" s="429"/><c r="G23" s="429"/><c r="I23" s="429"/><c r="J23" s="429"/><c r="K23" s="429"/><c r="L23" s="429"/><c r="M23" s="429"/><c r="N23" s="429"/><c r="O23" s="429"/></row><row r="24" spans="2:15"><c r="B24" s="429"/><c r="C24" s="429"/><c r="D24" s="429"/><c r="E24" s="429"/><c r="F24" s="429"/><c r="G24" s="429"/><c r="I24" s="429"/><c r="J24" s="429"/><c r="K24" s="429"/><c r="L24" s="429"/><c r="M24" s="429"/><c r="N24" s="429"/><c r="O24" s="429"/></row><row r="25" spans="2:15"><c r="B25" s="429"/><c r="C25" s="429"/><c r="D25" s="429"/><c r="E25" s="429"/><c r="F25" s="429"/><c r="G25" s="429"/><c r="I25" s="429"/><c r="J25" s="429"/><c r="K25" s="429"/><c r="L25" s="429"/><c r="M25" s="429"/><c r="N25" s="429"/><c r="O25" s="429"/></row><row r="26" spans="2:15"><c r="B26" s="429"/><c r="C26" s="429"/><c r="D26" s="429"/><c r="E26" s="429"/><c r="F26" s="429"/><c r="G26" s="429"/><c r="I26" s="429"/><c r="J26" s="429"/><c r="K26" s="429"/><c r="L26" s="429"/><c r="M26" s="429"/><c r="N26" s="429"/><c r="O26" s="429"/></row><row r="27" spans="2:15"><c r="B27" s="429"/><c r="C27" s="429"/><c r="D27" s="429"/><c r="E27" s="429"/><c r="F27" s="429"/><c r="G27" s="429"/><c r="I27" s="429"/><c r="J27" s="429"/><c r="K27" s="429"/><c r="L27" s="429"/><c r="M27" s="429"/><c r="N27" s="429"/><c r="O27" s="429"/></row><row r="28" spans="2:15"><c r="B28" s="429"/><c r="C28" s="429"/><c r="D28" s="429"/><c r="E28" s="429"/><c r="F28" s="429"/><c r="G28" s="429"/><c r="I28" s="429"/><c r="J28" s="429"/><c r="K28" s="429"/><c r="L28" s="429"/><c r="M28" s="429"/><c r="N28" s="429"/><c r="O28" s="429"/></row><row r="29" ht="14.25" spans="2:9"><c r="B29" s="178" t="s"><v>2453</v></c><c r="I29" s="178" t="s"><v>2454</v></c></row><row r="60" ht="14.25" spans="2:9"><c r="B60" s="178" t="s"><v>2455</v></c><c r="I60" s="178" t="s"><v>2456</v></c></row><row r="89" ht="14.25" spans="2:2"><c r="B89" s="178" t="s"><v>2457</v></c></row></sheetData><mergeCells count="3"><mergeCell ref="B1:J1"/><mergeCell ref="B4:G28"/><mergeCell ref="I4:O28"/></mergeCells><hyperlinks><hyperlink ref="A2" location="报价总目录!A1" display="返回目录"/></hyperlinks><pageMargins left="0.7" right="0.7" top="0.75" bottom="0.75" header="0.3" footer="0.3"/><headerFooter/><drawing r:id="rId1"/></worksheet>